Conversus/__init__.py
Conversus/api.py
Conversus/config.py
tests/__init__.py
conversus_api-0.0.6.dist-info/LICENSE
conversus_api-0.0.6.dist-info/METADATA
conversus_api-0.0.6.dist-info/WHEEL
conversus_api-0.0.6.dist-info/top_level.txt
conversus_api-0.0.6.dist-info/RECORD
