Metadata-Version: 2.1
Name: conversus-api
Version: 0.0.6
Summary: Python SDK for Conversus API
Home-page: https://github.com/converseon/conversus_sdk
Author: Anthony Bu
Author-email: abu@converseon.com
License: UNKNOWN
Platform: UNKNOWN
Classifier: Development Status :: 2 - Pre-Alpha
Classifier: Intended Audience :: Developers
Classifier: Programming Language :: Python :: 3
Classifier: License :: OSI Approved :: Apache Software License
Classifier: Operating System :: OS Independent
Requires-Dist: requests (>=2.22.0)
